vecmaths/__init__.py
vecmaths/_version.py
vecmaths/geometry.py
vecmaths/rotation.py
vecmaths/utils.py
vecmaths/vectors.py
vecmaths-0.1.6.dist-info/LICENSE
vecmaths-0.1.6.dist-info/METADATA
vecmaths-0.1.6.dist-info/WHEEL
vecmaths-0.1.6.dist-info/top_level.txt
vecmaths-0.1.6.dist-info/RECORD
